dummy/dummy/dummy.v
module dummy(
    input logic clk,
    input logic rst,
    output logic [3:0] count
);

    always_ff @(posedge clk) begin
        if (rst)
            count <= 0;
        else
            count <= count + 1;
    end

endmodule

dump.vcd
$version Generated by VerilatedVcd $end
$date Mon May  5 16:13:59 2025
 $end
$timescale   1ps $end

 $scope module TOP $end
  $var wire  1 # clk $end
  $var wire  4 % count [3:0] $end
  $var wire  1 $ rst $end
  $scope module dummy $end
   $var wire  1 # clk $end
   $var wire  4 % count [3:0] $end
   $var wire  1 $ rst $end
  $upscope $end
 $upscope $end
$enddefinitions $end


#0
0#
1$
b0000 %
#1
1#
#2
0#
#3
1#
#4
0#
0$
#5
1#
b0001 %
#6
0#
#7
1#
b0010 %
#8
0#
#9
1#
b0011 %
#10
0#
#11
1#
b0100 %
#12
0#
#13
1#
b0101 %
#14
0#
#15
1#
b0110 %
#16
0#
#17
1#
b0111 %
#18
0#
#19
1#
b1000 %
#20
0#
#21
1#
b1001 %
#22
0#
#23
1#
b1010 %
#24
0#
#25
1#
b1011 %
#26
0#
#27
1#
b1100 %
#28
0#
#29
1#
b1101 %
#30
0#
#31
1#
b1110 %
#32
0#
#33
1#
b1111 %
#34
0#
#35
1#
b0000 %
#36
0#
#37
1#
b0001 %
#38
0#
#39
1#
b0010 %
#40
0#
#41
1#
b0011 %
#42
0#
#43
1#
b0100 %
#44
0#
#45
1#
b0101 %
#46
0#
#47
1#
b0110 %
#48
0#
#49
1#
b0111 %
#50
0#
#51
1#
b1000 %
#52
0#
#53
1#
b1001 %
#54
0#
#55
1#
b1010 %
#56
0#
#57
1#
b1011 %
#58
0#
#59
1#
b1100 %
#60
0#
#61
1#
b1101 %
#62
0#
#63
1#
b1110 %
#64
0#
#65
1#
b1111 %
#66
0#
#67
1#
b0000 %
#68
0#
#69
1#
b0001 %
#70
0#
#71
1#
b0010 %
#72
0#
#73
1#
b0011 %
#74
0#
#75
1#
b0100 %
#76
0#
#77
1#
b0101 %
#78
0#
#79
1#
b0110 %
#80
0#
#81
1#
b0111 %
#82
0#
#83
1#
b1000 %
#84
0#
#85
1#
b1001 %
#86
0#
#87
1#
b1010 %
#88
0#
#89
1#
b1011 %
#90
0#
#91
1#
b1100 %
#92
0#
#93
1#
b1101 %
#94
0#
#95
1#
b1110 %
#96
0#
#97
1#
b1111 %
#98
0#
#99
1#
b0000 %
