pipelined_stall_doesnt_stall_on_flush/defines.vh
`define PIPELINE_DEPTH 3

`define ADDRESS_WIDTH 8
`define DATA_WIDTH 32
`define ID_WIDTH 8

`define RESOURCE_DELAY 10
`define RESOURCE_DELAY_COUNTER_WIDTH 4

global_stall/consumer.v
`include "defines.vh"

module consumer (
    input  wire clk,
    input  wire reset,

    input  wire [`DATA_WIDTH-1:0] in_data,
    input  wire [`ID_WIDTH-1:0]   in_id,
    input  wire                   in_valid
);
    // Consumer logic placeholder
    // This module would typically process the data received from the shared resource.
    // For this example, we will just output the data to a register.

    reg [`DATA_WIDTH-1:0]   data_reg;
    reg [`ID_WIDTH-1:0]     id_reg;
    reg                     valid_reg;

    always @(posedge clk or posedge reset) begin
        if (reset) begin
            data_reg <= 0;
            id_reg <= 0;
            valid_reg <= 0;
        end else if (in_valid) begin
            data_reg <= in_data;
            id_reg <= in_id;
            valid_reg <= 1; // Indicate that new data is available
        end else begin
            valid_reg <= 0; // No new data
        end
    end
endmodule

global_stall/shared_resource.v
`include "defines.vh"

module shared_resource (
    input  wire clk,
    input  wire reset,
    
    input  wire [`ADDRESS_WIDTH-1:0]    in_address,
    input  wire [`ID_WIDTH-1:0]         in_id,

    input  wire                         in_valid,

    output wire [`DATA_WIDTH-1:0]       out_data,
    output wire [`ID_WIDTH-1:0]         out_id,
    output wire                         out_valid,
    output wire                         out_ready
);
    reg [`DATA_WIDTH-1:0] reg_data_internal;
    reg [`ID_WIDTH-1:0]   reg_id_internal;
    reg [`DATA_WIDTH-1:0] reg_data_external;
    reg [`ID_WIDTH-1:0]   reg_id_external;
    reg reg_valid;
    reg reg_ready;

    reg [`RESOURCE_DELAY_COUNTER_WIDTH-1:0] counter;

    //reg [`RESOURCE_DELAY_COUNTER_WIDTH-1:0] ready_counter; //testing what happens with long_nonstall

    assign out_data = reg_data_external;
    assign out_id   = reg_id_external;
    assign out_valid = reg_valid;
    assign out_ready = reg_ready;

    always @(posedge clk or posedge reset) begin
        if (reset) begin
            reg_data_internal <= 0;
            reg_id_internal   <= 0;

            reg_data_external <= 0;
            reg_id_external   <= 0;

            reg_valid <= 0;
            reg_ready <= 1;

            counter <= 0;

	    //ready_counter <= 0;
        end else begin
            if (counter == 0) begin
                if (in_valid) begin // New data received, process it and wait
                    reg_data_internal <= { {`DATA_WIDTH-`ADDRESS_WIDTH{1'b0}}, in_address } + `DATA_WIDTH'b1000000000; // Simulate some processing
                    reg_id_internal   <= in_id;
                    counter <= 1;
                    reg_ready <= 0;
                end else begin // Wait for new data
                    counter <= 0;
                end
                reg_valid <= 0;
            end else if (counter < `RESOURCE_DELAY) begin // Fake processing delay
                counter <= counter + 1;
                reg_ready <= 0;
                reg_valid <= 0;
            end else begin // Processing done, output the data
                reg_data_external <= reg_data_internal;
                reg_id_external   <= reg_id_internal;
                reg_ready <= 1;
                reg_valid <= 1;
				//if (ready_counter < 4'hf) begin
				//	ready_counter <= ready_counter + 4'd1;
				//end else begin
					counter <= 0;
				//	ready_counter <= 4'd0;
				//end
            end
        end
    end
endmodule

pipelined_stall_noflush/pipeline_stage.v
`include "defines.vh"

module pipeline_stage (
    input  wire clk,
    input  wire reset,

    input  wire [`ADDRESS_WIDTH-1:0]    stage_offset,

    input  wire [`ADDRESS_WIDTH-1:0]    in_address,
    input  wire [`ID_WIDTH-1:0]         in_id,
    input  wire                         in_valid,
    output wire                         out_stall,

    output wire [`ADDRESS_WIDTH-1:0]    out_address, 
    output wire [`ID_WIDTH-1:0]         out_id,
    output wire                         out_valid,
    input  wire                         in_stall
);
    // Internal signals
    reg [`ADDRESS_WIDTH-1:0] reg_main_address;
    reg [`ID_WIDTH-1:0]      reg_main_id;
    reg                      reg_main_valid;

    reg [`ADDRESS_WIDTH-1:0] reg_overflow_address;
    reg [`ID_WIDTH-1:0]      reg_overflow_id;
    reg                      reg_overflow_valid;

	reg main_en;
	reg overflow_en;

	reg overflow_sel;

	assign main_en = !(in_stall && reg_main_valid);
	//assign overflow_en = (!main_en && !reg_overflow_valid); //if overflow isn't occupied and main is off
	assign overflow_en = (!in_stall && reg_overflow_valid && reg_main_valid) || (in_stall && !reg_overflow_valid && reg_main_valid);

    //reg head;
    //reg tail;

    // Output assignments
    assign out_address = reg_main_address;
    assign out_id      = reg_main_id;
    assign out_valid   = reg_main_valid;
    //assign out_stall   = in_stall;
    //assign out_stall   = in_stall && reg_main_valid && reg_overflow_valid; //if both reg's are occupied, stall the previous stage
	assign out_stall   = reg_overflow_valid;
	//the way this logic works, the input will be ignored for one cycle when unstalling. Might be fine is the previous stage should still be stalled, so it's input should carry on to the next cycle

    // main ff
    always_ff @(posedge clk or posedge reset) begin
        if (reset) begin
            reg_main_address <= 0;
            reg_main_id      <= 0;
            reg_main_valid   <= 0;
        end else if (main_en) begin
			if ((overflow_sel && reg_overflow_valid) || (!overflow_sel && in_valid)) begin
				reg_main_address <= (overflow_sel) ? reg_overflow_address : (in_address + stage_offset) & ((1 << `ADDRESS_WIDTH) - 1);
				reg_main_id      <= (overflow_sel) ? reg_overflow_id : in_id;
				reg_main_valid   <= 1;
			end else begin
				reg_main_valid   <= 0;
			end
        end
    end

	assign overflow_sel = reg_overflow_valid;

	
    // overflow ff
    always_ff @(posedge clk or posedge reset) begin
        if (reset) begin
            reg_overflow_address <= 0;
            reg_overflow_id      <= 0;
            reg_overflow_valid   <= 0;
        end else if (overflow_en) begin
			if (in_valid) begin
				reg_overflow_address <= (in_stall) ? (in_address + stage_offset) & ((1 << `ADDRESS_WIDTH) - 1) : 0;
				reg_overflow_id      <= (in_stall) ? in_id : 0;
				reg_overflow_valid   <= (in_stall) ? 1 : 0;
			end else begin
				reg_overflow_valid   <= 0;
			end
        end
    end

endmodule

pipelined_stall_noflush/pipeline.v
`include "defines.vh"

module pipeline (
    input  wire clk,
    input  wire reset,
    
    input  wire [`ADDRESS_WIDTH-1:0]    in_address,
    input  wire [`ID_WIDTH-1:0]         in_id,
    input  wire                         in_valid,
    output wire                         out_stall,

    output wire [`ADDRESS_WIDTH-1:0]    out_address,
    output wire [`ID_WIDTH-1:0]         out_id,
    output wire                         out_valid,
    input  wire                         in_stall
);
    // Predeclare forward-facing wires
    wire [`ADDRESS_WIDTH-1:0] address [`PIPELINE_DEPTH:0];
    wire [`ID_WIDTH-1:0]      id      [`PIPELINE_DEPTH:0];
    wire                      valid   [`PIPELINE_DEPTH:0];
    wire                      stall   [`PIPELINE_DEPTH:0];


    assign address[0] = in_address;
    assign id[0]      = in_id;
    assign valid[0]   = in_valid;
    assign out_stall = stall[0];

    assign out_address = address[`PIPELINE_DEPTH];
    assign out_id      = id[`PIPELINE_DEPTH];
    assign out_valid   = valid[`PIPELINE_DEPTH];
    assign stall[`PIPELINE_DEPTH] = in_stall;

    genvar i;
    generate
        for (i = 0; i < `PIPELINE_DEPTH; i = i + 1) begin : PIPELINE
            pipeline_stage stage_inst (
            .clk(clk),
            .reset(reset),

            .stage_offset((((i+1) * 3)) & ((1 << `ADDRESS_WIDTH) - 1)),  // jumble

            .in_address(address[i]),
            .in_id(id[i]),
            .in_valid(valid[i]),
            .out_stall(stall[i]),

            .out_address(address[i+1]),
            .out_id(id[i+1]),
            .out_valid(valid[i+1]),
            .in_stall(stall[i+1])
            );
        end
    endgenerate
endmodule

global_stall/arbiter.v
module arbiter (
    input  wire clk,
    input  wire reset,

    input  wire in_valid_1,
    input  wire in_valid_2,

    input  wire in_ready,

    output wire out_choice,
    output wire out_valid,

    output wire out_stall_1,
    output wire out_stall_2
);
    reg reg_choice;
    assign out_choice = reg_choice;

    assign out_stall_1 = in_valid_1 ? !(in_ready && !reg_choice) : 0;
    assign out_stall_2 = in_valid_2 ? !(in_ready && reg_choice) : 0;

    assign out_valid = in_valid_1 || in_valid_2;

    always @(posedge clk or posedge reset) begin
        if (reset) begin
            reg_choice   <= 0;
        end else begin
            if (in_ready) begin
                if (in_valid_1 && in_valid_2) begin
                    reg_choice <= !reg_choice;
                end else if (in_valid_1) begin
                    reg_choice <= 0;
                end else if (in_valid_2) begin
                    reg_choice <= 1;
                end
            end else begin
                reg_choice <= reg_choice;
            end
        end
    end
endmodule

pipelined_stall/producer.v
`include "defines.vh"

module producer (
    input  wire clk,
    input  wire reset,
    
    input  wire in_stall_1,
    output wire [`ADDRESS_WIDTH-1:0] out_address_1,
    output wire [`ID_WIDTH-1:0]      out_id_1,
    output wire                      out_valid_1,

    input  wire in_stall_2,
    output wire [`ADDRESS_WIDTH-1:0] out_address_2,
    output wire [`ID_WIDTH-1:0]      out_id_2,
    output wire                      out_valid_2
);
    // Registers
    reg [`ADDRESS_WIDTH-1:0] reg_address_1;
    reg [`ID_WIDTH-1:0]      reg_id_1;
    reg                      reg_valid_1;

    reg [`ADDRESS_WIDTH-1:0] reg_address_2;
    reg [`ID_WIDTH-1:0]      reg_id_2;
    reg                      reg_valid_2;

    // Output mappings
    assign out_address_1 = reg_address_1;
    assign out_id_1      = reg_id_1;
    assign out_valid_1   = reg_valid_1;
    
    assign out_address_2 = reg_address_2;
    assign out_id_2      = reg_id_2;
    assign out_valid_2   = reg_valid_2;

    // Sequential logic for producer
    always @(posedge clk or posedge reset) begin
        if (reset) begin
            reg_address_1 <= 0;
            reg_id_1      <= 0;

            reg_address_2 <= 0;
            reg_id_2      <= 0;
        end else begin
            if (!in_stall_1) begin
                reg_address_1 <= (reg_address_1 + 4) & ((1 << `ADDRESS_WIDTH) - 1);
                reg_id_1      <= {4'd1, (reg_id_1[3:0] + 4'b1)};
                reg_valid_1   <= 1;
            end

            if (!in_stall_2) begin
                reg_address_2 <= (reg_address_2 + 4) & ((1 << `ADDRESS_WIDTH) - 1);
                reg_id_2      <= {4'd2, (reg_id_1[3:0] + 4'b1)};
                reg_valid_2   <= 1;
            end
        end
    end
endmodule

pipelined_stall_noflush/top.v
`include "defines.vh"

module top (
    input wire clk,
    input wire reset
);
    wire [`ADDRESS_WIDTH-1:0]   start_address_1;
    wire [`ID_WIDTH-1:0]        start_id_1;
    wire                        start_valid_1;
    wire                        start_stall_1;

    wire [`ADDRESS_WIDTH-1:0]   start_address_2;
    wire [`ID_WIDTH-1:0]        start_id_2;
    wire                        start_valid_2;
    wire                        start_stall_2;

    producer producer (
        .clk(clk),
        .reset(reset),

        .in_stall_1(start_stall_1),
        .out_address_1(start_address_1),
        .out_id_1(start_id_1),
        .out_valid_1(start_valid_1),

        .in_stall_2(start_stall_2),
        .out_address_2(start_address_2),
        .out_id_2(start_id_2),
        .out_valid_2(start_valid_2)
    );

    wire [`ADDRESS_WIDTH-1:0]   end_address_1;
    wire [`ID_WIDTH-1:0]        end_id_1;
    wire                        end_valid_1;
    wire                        end_stall_1;

    wire [`ADDRESS_WIDTH-1:0]   end_address_2;
    wire [`ID_WIDTH-1:0]        end_id_2;
    wire                        end_valid_2;
    wire                        end_stall_2;

    wire                        arbiter_valid;
    wire                        arbiter_choice;

    arbiter arbiter (
        .clk(clk),
        .reset(reset),

        .in_valid_1(end_valid_1),
        .in_valid_2(end_valid_2),

        .in_ready(resource_ready),

        .out_choice(arbiter_choice),
        .out_valid(arbiter_valid),

        .out_stall_1(end_stall_1),
        .out_stall_2(end_stall_2)
    );

    pipeline pipeline_1 (
        .clk(clk),
        .reset(reset),
        
        .in_address(start_address_1),
        .in_id(start_id_1),
        .in_valid(start_valid_1),
        .out_stall(start_stall_1),

        .out_address(end_address_1),
        .out_id(end_id_1),
        .out_valid(end_valid_1),
        .in_stall(end_stall_1)
    );

    pipeline pipeline_2 (
        .clk(clk),
        .reset(reset),

        .in_address(start_address_2),
        .in_id(start_id_2),
        .in_valid(start_valid_2),
        .out_stall(start_stall_2),

        .out_address(end_address_2),
        .out_id(end_id_2),
        .out_valid(end_valid_2),
        .in_stall(end_stall_2)
    );

    wire [`DATA_WIDTH-1:0]  resource_data;
    wire [`ID_WIDTH-1:0]    resource_id;
    wire                    resource_valid;
    wire                    resource_ready;

    shared_resource shared_resource (
        .clk(clk),
        .reset(reset),

        .in_address(!arbiter_choice ? end_address_1 : end_address_2),
        .in_id(!arbiter_choice ? end_id_1 : end_id_2),

        .in_valid(arbiter_valid),

        .out_data(resource_data),
        .out_id(resource_id),
        .out_ready(resource_ready),
        .out_valid(resource_valid)
    );

    consumer consumer (
        .clk(clk),
        .reset(reset),

        .in_data(resource_data),
        .in_id(resource_id),
        .in_valid(resource_valid)
    );
endmodule

pipelined_stall_noflush/dump.vcd
$version Generated by VerilatedVcd $end
$date Sun May 11 17:07:29 2025
 $end
$timescale   1ns $end

 $scope module TOP $end
  $var wire  1 I+ clk $end
  $var wire  1 Q+ reset $end
  $scope module top $end
   $var wire  1 I' arbiter_choice $end
   $var wire  1 s arbiter_valid $end
   $var wire  1 I+ clk $end
   $var wire  8 3 end_address_1 [7:0] $end
   $var wire  8 S end_address_2 [7:0] $end
   $var wire  8 ; end_id_1 [7:0] $end
   $var wire  8 [ end_id_2 [7:0] $end
   $var wire  1 K end_stall_1 $end
   $var wire  1 k end_stall_2 $end
   $var wire  1 C end_valid_1 $end
   $var wire  1 c end_valid_2 $end
   $var wire  1 Q+ reset $end
   $var wire 32 Q' resource_data [31:0] $end
   $var wire  8 Y' resource_id [7:0] $end
   $var wire  1 i' resource_ready $end
   $var wire  1 a' resource_valid $end
   $var wire  8 w& start_address_1 [7:0] $end
   $var wire  8 1' start_address_2 [7:0] $end
   $var wire  8 !' start_id_1 [7:0] $end
   $var wire  8 9' start_id_2 [7:0] $end
   $var wire  1 # start_stall_1 $end
   $var wire  1 + start_stall_2 $end
   $var wire  1 )' start_valid_1 $end
   $var wire  1 A' start_valid_2 $end
   $scope module arbiter $end
    $var wire  1 I+ clk $end
    $var wire  1 i' in_ready $end
    $var wire  1 C in_valid_1 $end
    $var wire  1 c in_valid_2 $end
    $var wire  1 I' out_choice $end
    $var wire  1 K out_stall_1 $end
    $var wire  1 k out_stall_2 $end
    $var wire  1 s out_valid $end
    $var wire  1 I' reg_choice $end
    $var wire  1 Q+ reset $end
   $upscope $end
   $scope module consumer $end
    $var wire  1 I+ clk $end
    $var wire 32 1+ data_reg [31:0] $end
    $var wire  8 9+ id_reg [7:0] $end
    $var wire 32 Q' in_data [31:0] $end
    $var wire  8 Y' in_id [7:0] $end
    $var wire  1 a' in_valid $end
    $var wire  1 Q+ reset $end
    $var wire  1 A+ valid_reg $end
   $upscope $end
   $scope module pipeline_1 $end
    $var wire  8 { address(0) [7:0] $end
    $var wire  8 | address(1) [7:0] $end
    $var wire  8 } address(2) [7:0] $end
    $var wire  8 ~ address(3) [7:0] $end
    $var wire  1 I+ clk $end
    $var wire  8 =! id(0) [7:0] $end
    $var wire  8 >! id(1) [7:0] $end
    $var wire  8 ?! id(2) [7:0] $end
    $var wire  8 @! id(3) [7:0] $end
    $var wire  8 w& in_address [7:0] $end
    $var wire  8 !' in_id [7:0] $end
    $var wire  1 K in_stall $end
    $var wire  1 )' in_valid $end
    $var wire  8 3 out_address [7:0] $end
    $var wire  8 ; out_id [7:0] $end
    $var wire  1 # out_stall $end
    $var wire  1 C out_valid $end
    $var wire  1 Q+ reset $end
    $var wire  1 }! stall(0) $end
    $var wire  1 ~! stall(1) $end
    $var wire  1 !" stall(2) $end
    $var wire  1 "" stall(3) $end
    $var wire  1 ]! valid(0) $end
    $var wire  1 ^! valid(1) $end
    $var wire  1 _! valid(2) $end
    $var wire  1 `! valid(3) $end
    $scope module PIPELINE(0) $end
     $scope module stage_inst $end
      $var wire  1 I+ clk $end
      $var wire  8 ?" in_address [7:0] $end
      $var wire  8 G" in_id [7:0] $end
      $var wire  1 W" in_stall $end
      $var wire  1 O" in_valid $end
      $var wire  1 _" main_en $end
      $var wire  8 y' out_address [7:0] $end
      $var wire  8 #( out_id [7:0] $end
      $var wire  1 q' out_stall $end
      $var wire  1 +( out_valid $end
      $var wire  1 g" overflow_en $end
      $var wire  1 q' overflow_sel $end
      $var wire  8 y' reg_main_address [7:0] $end
      $var wire  8 #( reg_main_id [7:0] $end
      $var wire  1 +( reg_main_valid $end
      $var wire  8 3( reg_overflow_address [7:0] $end
      $var wire  8 ;( reg_overflow_id [7:0] $end
      $var wire  1 q' reg_overflow_valid $end
      $var wire  1 Q+ reset $end
      $var wire  8 Y+ stage_offset [7:0] $end
     $upscope $end
    $upscope $end
    $scope module PIPELINE(1) $end
     $scope module stage_inst $end
      $var wire  1 I+ clk $end
      $var wire  8 o" in_address [7:0] $end
      $var wire  8 w" in_id [7:0] $end
      $var wire  1 )# in_stall $end
      $var wire  1 !# in_valid $end
      $var wire  1 1# main_en $end
      $var wire  8 K( out_address [7:0] $end
      $var wire  8 S( out_id [7:0] $end
      $var wire  1 C( out_stall $end
      $var wire  1 [( out_valid $end
      $var wire  1 9# overflow_en $end
      $var wire  1 C( overflow_sel $end
      $var wire  8 K( reg_main_address [7:0] $end
      $var wire  8 S( reg_main_id [7:0] $end
      $var wire  1 [( reg_main_valid $end
      $var wire  8 c( reg_overflow_address [7:0] $end
      $var wire  8 k( reg_overflow_id [7:0] $end
      $var wire  1 C( reg_overflow_valid $end
      $var wire  1 Q+ reset $end
      $var wire  8 a+ stage_offset [7:0] $end
     $upscope $end
    $upscope $end
    $scope module PIPELINE(2) $end
     $scope module stage_inst $end
      $var wire  1 I+ clk $end
      $var wire  8 A# in_address [7:0] $end
      $var wire  8 I# in_id [7:0] $end
      $var wire  1 Y# in_stall $end
      $var wire  1 Q# in_valid $end
      $var wire  1 a# main_en $end
      $var wire  8 {( out_address [7:0] $end
      $var wire  8 %) out_id [7:0] $end
      $var wire  1 s( out_stall $end
      $var wire  1 -) out_valid $end
      $var wire  1 i# overflow_en $end
      $var wire  1 s( overflow_sel $end
      $var wire  8 {( reg_main_address [7:0] $end
      $var wire  8 %) reg_main_id [7:0] $end
      $var wire  1 -) reg_main_valid $end
      $var wire  8 5) reg_overflow_address [7:0] $end
      $var wire  8 =) reg_overflow_id [7:0] $end
      $var wire  1 s( reg_overflow_valid $end
      $var wire  1 Q+ reset $end
      $var wire  8 i+ stage_offset [7:0] $end
     $upscope $end
    $upscope $end
   $upscope $end
   $scope module pipeline_2 $end
    $var wire  8 q# address(0) [7:0] $end
    $var wire  8 r# address(1) [7:0] $end
    $var wire  8 s# address(2) [7:0] $end
    $var wire  8 t# address(3) [7:0] $end
    $var wire  1 I+ clk $end
    $var wire  8 3$ id(0) [7:0] $end
    $var wire  8 4$ id(1) [7:0] $end
    $var wire  8 5$ id(2) [7:0] $end
    $var wire  8 6$ id(3) [7:0] $end
    $var wire  8 1' in_address [7:0] $end
    $var wire  8 9' in_id [7:0] $end
    $var wire  1 k in_stall $end
    $var wire  1 A' in_valid $end
    $var wire  8 S out_address [7:0] $end
    $var wire  8 [ out_id [7:0] $end
    $var wire  1 + out_stall $end
    $var wire  1 c out_valid $end
    $var wire  1 Q+ reset $end
    $var wire  1 s$ stall(0) $end
    $var wire  1 t$ stall(1) $end
    $var wire  1 u$ stall(2) $end
    $var wire  1 v$ stall(3) $end
    $var wire  1 S$ valid(0) $end
    $var wire  1 T$ valid(1) $end
    $var wire  1 U$ valid(2) $end
    $var wire  1 V$ valid(3) $end
    $scope module PIPELINE(0) $end
     $scope module stage_inst $end
      $var wire  1 I+ clk $end
      $var wire  8 5% in_address [7:0] $end
      $var wire  8 =% in_id [7:0] $end
      $var wire  1 M% in_stall $end
      $var wire  1 E% in_valid $end
      $var wire  1 U% main_en $end
      $var wire  8 M) out_address [7:0] $end
      $var wire  8 U) out_id [7:0] $end
      $var wire  1 E) out_stall $end
      $var wire  1 ]) out_valid $end
      $var wire  1 ]% overflow_en $end
      $var wire  1 E) overflow_sel $end
      $var wire  8 M) reg_main_address [7:0] $end
      $var wire  8 U) reg_main_id [7:0] $end
      $var wire  1 ]) reg_main_valid $end
      $var wire  8 e) reg_overflow_address [7:0] $end
      $var wire  8 m) reg_overflow_id [7:0] $end
      $var wire  1 E) reg_overflow_valid $end
      $var wire  1 Q+ reset $end
      $var wire  8 Y+ stage_offset [7:0] $end
     $upscope $end
    $upscope $end
    $scope module PIPELINE(1) $end
     $scope module stage_inst $end
      $var wire  1 I+ clk $end
      $var wire  8 e% in_address [7:0] $end
      $var wire  8 m% in_id [7:0] $end
      $var wire  1 }% in_stall $end
      $var wire  1 u% in_valid $end
      $var wire  1 '& main_en $end
      $var wire  8 }) out_address [7:0] $end
      $var wire  8 '* out_id [7:0] $end
      $var wire  1 u) out_stall $end
      $var wire  1 /* out_valid $end
      $var wire  1 /& overflow_en $end
      $var wire  1 u) overflow_sel $end
      $var wire  8 }) reg_main_address [7:0] $end
      $var wire  8 '* reg_main_id [7:0] $end
      $var wire  1 /* reg_main_valid $end
      $var wire  8 7* reg_overflow_address [7:0] $end
      $var wire  8 ?* reg_overflow_id [7:0] $end
      $var wire  1 u) reg_overflow_valid $end
      $var wire  1 Q+ reset $end
      $var wire  8 a+ stage_offset [7:0] $end
     $upscope $end
    $upscope $end
    $scope module PIPELINE(2) $end
     $scope module stage_inst $end
      $var wire  1 I+ clk $end
      $var wire  8 7& in_address [7:0] $end
      $var wire  8 ?& in_id [7:0] $end
      $var wire  1 O& in_stall $end
      $var wire  1 G& in_valid $end
      $var wire  1 W& main_en $end
      $var wire  8 O* out_address [7:0] $end
      $var wire  8 W* out_id [7:0] $end
      $var wire  1 G* out_stall $end
      $var wire  1 _* out_valid $end
      $var wire  1 _& overflow_en $end
      $var wire  1 G* overflow_sel $end
      $var wire  8 O* reg_main_address [7:0] $end
      $var wire  8 W* reg_main_id [7:0] $end
      $var wire  1 _* reg_main_valid $end
      $var wire  8 g* reg_overflow_address [7:0] $end
      $var wire  8 o* reg_overflow_id [7:0] $end
      $var wire  1 G* reg_overflow_valid $end
      $var wire  1 Q+ reset $end
      $var wire  8 i+ stage_offset [7:0] $end
     $upscope $end
    $upscope $end
   $upscope $end
   $scope module producer $end
    $var wire  1 I+ clk $end
    $var wire  1 # in_stall_1 $end
    $var wire  1 + in_stall_2 $end
    $var wire  8 w& out_address_1 [7:0] $end
    $var wire  8 1' out_address_2 [7:0] $end
    $var wire  8 !' out_id_1 [7:0] $end
    $var wire  8 9' out_id_2 [7:0] $end
    $var wire  1 )' out_valid_1 $end
    $var wire  1 A' out_valid_2 $end
    $var wire  8 w& reg_address_1 [7:0] $end
    $var wire  8 1' reg_address_2 [7:0] $end
    $var wire  8 !' reg_id_1 [7:0] $end
    $var wire  8 9' reg_id_2 [7:0] $end
    $var wire  1 )' reg_valid_1 $end
    $var wire  1 A' reg_valid_2 $end
    $var wire  1 Q+ reset $end
   $upscope $end
   $scope module shared_resource $end
    $var wire  1 I+ clk $end
    $var wire  4 )+ counter [3:0] $end
    $var wire  8 g& in_address [7:0] $end
    $var wire  8 o& in_id [7:0] $end
    $var wire  1 s in_valid $end
    $var wire 32 Q' out_data [31:0] $end
    $var wire  8 Y' out_id [7:0] $end
    $var wire  1 i' out_ready $end
    $var wire  1 a' out_valid $end
    $var wire 32 Q' reg_data_external [31:0] $end
    $var wire 32 w* reg_data_internal [31:0] $end
    $var wire  8 Y' reg_id_external [7:0] $end
    $var wire  8 !+ reg_id_internal [7:0] $end
    $var wire  1 i' reg_ready $end
    $var wire  1 a' reg_valid $end
    $var wire  1 Q+ reset $end
   $upscope $end
  $upscope $end
 $upscope $end
$enddefinitions $end


#0
0#
0+
b00000000 3
b00000000 ;
0C
0K
b00000000 S
b00000000 [
0c
0k
0s
b00000000 {
b00000000 |
b00000000 }
b00000000 ~
b00000000 =!
b00000000 >!
b00000000 ?!
b00000000 @!
0]!
0^!
0_!
0`!
0}!
0~!
0!"
0""
b00000000 ?"
b00000000 G"
0O"
0W"
1_"
0g"
b00000000 o"
b00000000 w"
0!#
0)#
11#
09#
b00000000 A#
b00000000 I#
0Q#
0Y#
1a#
0i#
b00000000 q#
b00000000 r#
b00000000 s#
b00000000 t#
b00000000 3$
b00000000 4$
b00000000 5$
b00000000 6$
0S$
0T$
0U$
0V$
0s$
0t$
0u$
0v$
b00000000 5%
b00000000 =%
0E%
0M%
1U%
0]%
b00000000 e%
b00000000 m%
0u%
0}%
1'&
0/&
b00000000 7&
b00000000 ?&
0G&
0O&
1W&
0_&
b00000000 g&
b00000000 o&
b00000000 w&
b00000000 !'
0)'
b00000000 1'
b00000000 9'
0A'
0I'
b00000000000000000000000000000000 Q'
b00000000 Y'
0a'
0i'
0q'
b00000000 y'
b00000000 #(
0+(
b00000000 3(
b00000000 ;(
0C(
b00000000 K(
b00000000 S(
0[(
b00000000 c(
b00000000 k(
0s(
b00000000 {(
b00000000 %)
0-)
b00000000 5)
b00000000 =)
0E)
b00000000 M)
b00000000 U)
0])
b00000000 e)
b00000000 m)
0u)
b00000000 })
b00000000 '*
0/*
b00000000 7*
b00000000 ?*
0G*
b00000000 O*
b00000000 W*
0_*
b00000000 g*
b00000000 o*
b00000000000000000000000000000000 w*
b00000000 !+
b0000 )+
b00000000000000000000000000000000 1+
b00000000 9+
0A+
1I+
1Q+
b00000011 Y+
b00000110 a+
b00001001 i+
#1
0I+
#2
1i'
1I+
#3
0I+
#4
1I+
#5
0I+
#6
1I+
#7
0I+
#8
1I+
#9
0I+
#10
1I+
#11
0I+
#12
1I+
#13
0I+
#14
1I+
#15
0I+
#16
1I+
#17
0I+
#18
1I+
#19
0I+
#20
1I+
#21
0I+
0Q+
#22
b00000100 {
b00010001 =!
1]!
b00000100 ?"
b00010001 G"
1O"
b00000100 q#
b00100001 3$
1S$
b00000100 5%
b00100001 =%
1E%
b00000100 w&
b00010001 !'
1)'
b00000100 1'
b00100001 9'
1A'
1I+
#23
0I+
#24
b00001000 {
b00000111 |
b00010010 =!
b00010001 >!
1^!
b00001000 ?"
b00010010 G"
b00000111 o"
b00010001 w"
1!#
b00001000 q#
b00000111 r#
b00100010 3$
b00100001 4$
1T$
b00001000 5%
b00100010 =%
b00000111 e%
b00100001 m%
1u%
b00001000 w&
b00010010 !'
b00001000 1'
b00100010 9'
b00000111 y'
b00010001 #(
1+(
b00000111 M)
b00100001 U)
1])
1I+
#25
0I+
#26
b00001100 {
b00001011 |
b00001101 }
b00010011 =!
b00010010 >!
b00010001 ?!
1_!
b00001100 ?"
b00010011 G"
b00001011 o"
b00010010 w"
b00001101 A#
b00010001 I#
1Q#
b00001100 q#
b00001011 r#
b00001101 s#
b00100011 3$
b00100010 4$
b00100001 5$
1U$
b00001100 5%
b00100011 =%
b00001011 e%
b00100010 m%
b00001101 7&
b00100001 ?&
1G&
b00001100 w&
b00010011 !'
b00001100 1'
b00100011 9'
b00001011 y'
b00010010 #(
b00001101 K(
b00010001 S(
1[(
b00001011 M)
b00100010 U)
b00001101 })
b00100001 '*
1/*
1I+
#27
0I+
#28
b00010110 3
b00010001 ;
1C
b00010110 S
b00100001 [
1c
1k
1s
b00010000 {
b00001111 |
b00010001 }
b00010110 ~
b00010100 =!
b00010011 >!
b00010010 ?!
b00010001 @!
1`!
b00010000 ?"
b00010100 G"
b00001111 o"
b00010011 w"
b00010001 A#
b00010010 I#
b00010000 q#
b00001111 r#
b00010001 s#
b00010110 t#
b00100100 3$
b00100011 4$
b00100010 5$
b00100001 6$
1V$
1v$
b00010000 5%
b00100100 =%
b00001111 e%
b00100011 m%
b00010001 7&
b00100010 ?&
1O&
0W&
1_&
b00010110 g&
b00010001 o&
b00010000 w&
b00010100 !'
b00010000 1'
b00100100 9'
b00001111 y'
b00010011 #(
b00010001 K(
b00010010 S(
b00010110 {(
b00010001 %)
1-)
b00001111 M)
b00100011 U)
b00010001 })
b00100010 '*
b00010110 O*
b00100001 W*
1_*
1I+
#29
0I+
#30
b00011010 3
b00010010 ;
1K
b00010100 {
b00010011 |
b00010101 }
b00011010 ~
b00010101 =!
b00010100 >!
b00010011 ?!
b00010010 @!
1""
b00010100 ?"
b00010101 G"
b00010011 o"
b00010100 w"
b00010101 A#
b00010011 I#
1Y#
0a#
1i#
b00010100 q#
b00010011 r#
b00010101 s#
b00100101 3$
b00100100 4$
b00100011 5$
1u$
b00010100 5%
b00100101 =%
b00010011 e%
b00100100 m%
1}%
0'&
1/&
b00010101 7&
b00100011 ?&
0_&
b00100001 o&
b00010100 w&
b00010101 !'
b00010100 1'
b00100101 9'
1I'
0i'
b00010011 y'
b00010100 #(
b00010101 K(
b00010011 S(
b00011010 {(
b00010010 %)
b00010011 M)
b00100100 U)
b00010101 })
b00100011 '*
1G*
b00011010 g*
b00100010 o*
b00000000000000000000001000010110 w*
b00010001 !+
b0001 )+
1I+
#31
0I+
#32
b00011000 {
b00010111 |
b00011001 }
b00010110 =!
b00010101 >!
b00010100 ?!
1!"
b00011000 ?"
b00010110 G"
b00010111 o"
b00010101 w"
1)#
01#
19#
b00011001 A#
b00010100 I#
0i#
b00011000 q#
b00010111 r#
b00100110 3$
b00100101 4$
1t$
b00011000 5%
b00100110 =%
1M%
0U%
1]%
b00010111 e%
b00100101 m%
0/&
b00011000 w&
b00010110 !'
b00011000 1'
b00100110 9'
b00010111 y'
b00010101 #(
b00011001 K(
b00010100 S(
1s(
b00011110 5)
b00010011 =)
b00010111 M)
b00100101 U)
1u)
b00011001 7*
b00100100 ?*
b0010 )+
1I+
#33
0I+
#34
1+
b00011100 {
b00011011 |
b00010111 =!
b00010110 >!
1~!
b00011100 ?"
b00010111 G"
1W"
0_"
1g"
b00011011 o"
b00010110 w"
09#
b00011100 q#
b00100111 3$
1s$
b00011100 5%
b00100111 =%
0]%
b00011100 w&
b00010111 !'
b00011100 1'
b00100111 9'
b00011011 y'
b00010110 #(
1C(
b00011101 c(
b00010101 k(
1E)
b00011011 e)
b00100110 m)
b0011 )+
1I+
#35
0I+
